histolytics/__init__.py
histolytics/py.typed
histolytics/data/__init__.py
histolytics/data/cancer_nuclei.parquet
histolytics/data/cancer_tissue.parquet
histolytics/data/cervix_biopsy_nuclei.parquet
histolytics/data/cervix_biopsy_tissue.parquet
histolytics/data/cervix_nuclei_crop.parquet
histolytics/data/cervix_tissue_crop.parquet
histolytics/data/fetch.py
histolytics/data/hgsc_nest.jpg
histolytics/data/hgsc_nest.parquet
histolytics/data/hgsc_nest_inst_mask.npz
histolytics/data/hgsc_nest_type_mask.npz
histolytics/data/hgsc_nuclei_wsi.parquet
histolytics/data/hgsc_stromal_cells.parquet
histolytics/data/hgsc_stromal_he.jpg
histolytics/data/hgsc_tissue_wsi.parquet
histolytics/losses/__init__.py
histolytics/metrics/__init__.py
histolytics/models/__init__.py
histolytics/models/_base_model.py
histolytics/models/cellpose_panoptic.py
histolytics/models/cellvit_panoptic.py
histolytics/models/cppnet_panoptic.py
histolytics/models/hovernet_panoptic.py
histolytics/models/stardist_panoptic.py
histolytics/nuc_feats/__init__.py
histolytics/nuc_feats/chromatin.py
histolytics/nuc_feats/intensity.py
histolytics/nuc_feats/texture.py
histolytics/spatial_agg/__init__.py
histolytics/spatial_agg/diversity.py
histolytics/spatial_agg/grid_agg.py
histolytics/spatial_agg/local_character.py
histolytics/spatial_agg/local_distances.py
histolytics/spatial_agg/local_diversity.py
histolytics/spatial_agg/local_values.py
histolytics/spatial_agg/reduce.py
histolytics/spatial_clust/__init__.py
histolytics/spatial_clust/autocorr.py
histolytics/spatial_clust/centrography.py
histolytics/spatial_clust/clust_metrics.py
histolytics/spatial_clust/density_clustering.py
histolytics/spatial_clust/lisa_clustering.py
histolytics/spatial_clust/ripley.py
histolytics/spatial_geom/__init__.py
histolytics/spatial_geom/axis.py
histolytics/spatial_geom/hull.py
histolytics/spatial_geom/line_metrics.py
histolytics/spatial_geom/medial_lines.py
histolytics/spatial_geom/morphometrics.py
histolytics-0.2.5.dist-info/METADATA
histolytics-0.2.5.dist-info/WHEEL
histolytics-0.2.5.dist-info/licenses/LICENSE
histolytics-0.2.5.dist-info/RECORD
