Metadata-Version: 2.4
Name: histolytics
Version: 0.2.5
Summary: Panoptic Segmentation and WSI Spatial Analysis
Project-URL: Homepage, https://hautaniemilab.github.io/histolytics/
Project-URL: Documentation, https://hautaniemilab.github.io/histolytics/
Project-URL: Repository, https://github.com/HautaniemiLab/histolytics
Project-URL: Changelog, https://github.com/HautaniemiLab/histolytics/blob/main/CHANGELOG.md
Author-email: Oskari Lehtonen <oskari.lehtonen@helsinki.fi>
License: BSD 3-Clause License
License-File: LICENSE
Keywords: computer vision,geospatial,panoptic segmentation,spatial analysis,whole slide image
Classifier: Programming Language :: Python :: 3
Classifier: Programming Language :: Python :: 3.10
Classifier: Programming Language :: Python :: 3.11
Classifier: Programming Language :: Python :: 3.12
Classifier: Programming Language :: Python :: 3.13
Requires-Python: >=3.10
Requires-Dist: albumentations>=2.0.6
Requires-Dist: cellseg-models-pytorch>=0.1.30
Requires-Dist: cucim-cu12>=25.6.0
Requires-Dist: cuml-cu12>=25.6.0
Requires-Dist: datasets>=3.6.0
Requires-Dist: esda>=2.7.0
Requires-Dist: geopandas>=1.0.1
Requires-Dist: h3>=4.2.2
Requires-Dist: libpysal>=4.13.0
Requires-Dist: mapclassify>=2.8.1
Requires-Dist: matplotlib>=3.10.3
Requires-Dist: networkx>=3.4.2
Requires-Dist: pandarallel>=1.6.5
Requires-Dist: quadbin>=0.2.2
Requires-Dist: scikit-image>=0.25.0
Requires-Dist: torchdata>=0.11.0
